omniblack/string_case/__init__.py
omniblack.string_case-0.0.2.dist-info/LICENSE.txt
omniblack.string_case-0.0.2.dist-info/METADATA
omniblack.string_case-0.0.2.dist-info/WHEEL
omniblack.string_case-0.0.2.dist-info/omniblack_package.json
omniblack.string_case-0.0.2.dist-info/omniblack_package.yaml
omniblack.string_case-0.0.2.dist-info/top_level.txt
omniblack.string_case-0.0.2.dist-info/RECORD
