Metadata-Version: 2.1
Name: omniblack.string-case
Version: 0.0.2
Author-email: Terry Patterson <Terryp@wegrok.net>
License: 
Project-URL: Homepage, https://gitlab.com/terryp/terry/-/tree/next/lib/string_case
Project-URL: Repository, https://gitlab.com/terryp/terry.git
License-File: LICENSE.txt
Requires-Dist: omniblack.utils
Provides-Extra: unicode
Requires-Dist: regex ; extra == 'unicode'
